toga_view/__init__.py
toga_view/__main__.py
toga_view/exceptions.py
toga_view/inspector.py
toga_view/archivers/__init__.py
toga_view/archivers/json_archiver.py
toga_view/archivers/xml_archiver.py
toga_view/parsers/__init__.py
toga_view/parsers/json_parser.py
toga_view/parsers/xml_parser.py
toga_view-0.0.1.dist-info/entry_points.txt
toga_view-0.0.1.dist-info/LICENSE
toga_view-0.0.1.dist-info/WHEEL
toga_view-0.0.1.dist-info/METADATA
toga_view-0.0.1.dist-info/RECORD
