Metadata-Version: 2.1
Name: toga-view
Version: 0.0.1
Summary: xml/json view support for toga
Keywords: beeware,toga,toga-echosystem,ui
Author-email: somehitDev <this.dev.somehit@gmail.com>
Requires-Python: >=3.8
Classifier: License :: OSI Approved :: MIT License
Classifier: Operating System :: POSIX
Classifier: Operating System :: MacOS :: MacOS X
Classifier: Operating System :: Microsoft :: Windows
Classifier: Programming Language :: Python :: 3.8
Classifier: Programming Language :: Python :: 3.9
Classifier: Programming Language :: Python :: 3.10
Classifier: Programming Language :: Python :: 3.11
Classifier: Programming Language :: Python :: 3.12
Requires-Dist: toga==0.4.5
Project-URL: Repository, https://github.com/somehitDev/toga-view
